{"id":"aladdin--764586654279121067","name":"Aladdin","otherName":"","level":4000000,"picture":"aladdin--764586654279121067.jpg","powers":["Acausality","Astral Projection","Astral Travel","Attack Negation","Attack Reflection","Blessed","Chaos Magic","Clairvoyance","Conceptual Manipulation","Corruption Resistance","Cosmic Awareness","Creation","Curse Manipulation","Deconstruction","Dimensional Awareness","Dimensional Travel","Energy Absorption","Energy Constructs","Energy Manipulation","Enhanced Senses","Extrasensory Perception","Fate Resistance","Immortality","Information Analysis","Law Manipulation","Magic","Magic Resistance","Mind Control Resistance","Morality Manipulation","Non-Physical Interaction","Power Nullifier","Purification","Soul Manipulation","Soul Resistance","Summoning","Absorption","Adaptation","Age Manipulation","Animal Control","Causality Manipulation","Damage Transferal","Danger Sense","Darkforce Manipulation","Durability Negation","Existence Erasure","Existence Erasure Resistance","Flight","Force Fields","Higher Dimensional Manipulation","Illusions","Power Sense"],"origin":"/aladdin/10-21897/","alignment":"Hero"}