{"id":"alya-cesaire-3905033230577714340","name":"Rena Rouge","otherName":"Alya Cesaire","level":353,"picture":"alya-cesaire-3905033230577714340.jpg","powers":["Agility","Cloaking","Enhanced Condition","Illumination","Illusions","Intelligence","Jump","Power Suit","Projection","Reflexes","Supernatural Condition","Acrobatics","Endurance","Grappling/Climbing","Hunters Instinct","Information Analysis","Stealth","Surface Scaling","Weapon Summoning","Weapons Master","Master Martial Artist","Zenith"],"origin":"/rena-rouge/10-39354/","alignment":"Hero"}