{"id":"carl-creel-2738145343307137348","name":"Absorbing Man","otherName":"Carl Creel","level":1000,"picture":"carl-creel-2738145343307137348.jpg","powers":["Absorption","Duplication","Durability","Energy Absorption","Intelligence","Invulnerability","Matter Absorption","Mind Control","Molecular Manipulation","Natural Armor","Power Absorption","Radiation Absorption","Radiation Immunity","Super Strength","Transformation","Accelerated Healing","Electrokinesis","Energy Manipulation","Fusion","Immortality","Regeneration","Weapons Master","Intangibility","Size Changing","Stealth"],"origin":"/absorbing-man/10-1448/","alignment":"Villain"}