{"id":"chaos--1052245269808461127","name":"Chaos","otherName":"","level":18000000,"picture":"chaos--1052245269808461127.jpg","powers":["Absorption","Avatar Creation","Chaos Manipulation","Cosmic Awareness","Energy Manipulation","Enhanced Senses","Intangibility","Nigh-Omnipresence","Non-Corporeal","Possession","Reality Warping","Regeneration","Teleportation","Dimensional Travel","Dream Manipulation","Durability Negation","Existence Erasure","Flight","Force Fields","Illusions","Immortality","Matter Manipulation","Non-Physical Interaction","Power Bestowal","Sleep Manipulation","Soul Manipulation","Time Travel"],"origin":"/chaos/10-21567/","alignment":"Villain"}