{"id":"corvus-glaive--6713267335379923255","name":"Corvus Glaive","otherName":"","level":191,"picture":"corvus-glaive--6713267335379923255.jpg","powers":["Acrobatics","Agility","Durability","Master Tactician","Peak Human Condition","Reflexes","Stamina","Super Speed","Super Strength","Weapons Master","Cold Resistance","Endurance","Enhanced Hearing","Enhanced Senses","Enhanced Sight","Enhanced Smell","Heat Resistance","Immortality","Jump","Marksmanship","Master Martial Artist","Stealth","Weapon-based Powers"],"origin":"/corvus-glaive/10-24361/","alignment":"Villain"}