{"id":"decidueye-2801770636299683054","name":"Decidueye","otherName":"","level":1000,"picture":"decidueye-2801770636299683054.jpg","powers":["Animal Attributes","Curse Manipulation","Damage Boost","Dexterity","Durability","Endurance","Enhanced Senses","Enhanced Sight","Flight","Hunters Instinct","Marksmanship","Non-Physical Interaction","Plant Control","Reflexes","Stamina","Statistics Amplification","Status Effect Inducement","Stealth","Super Speed","Super Strength","Ability Shift","Accelerated Healing","Acrobatics","Animal Oriented Powers","Damage Reduction","Durability Negation","Electricity Resistance","Enhanced Hearing","Force Fields","Gliding","Master Martial Artist","Master Tactician","Natural Weapons","Paralysis","Radar Sense","Reactive Evolution","Reactive Power Level","Statistics Reduction","Weapon-based Powers","Weapons Master","Attack Negation","Danger Sense","Danmaku","Duplication","Energy Beams","Energy Blasts","Energy Manipulation","Enhanced Smell","Light Control","Love Inducement","Metal Manipulation","Non-Corporeal","Weather Control"],"origin":"/decidueye/10-40602/","alignment":"Hero"}