{"id":"filius-flitwick-6980268984228399346","name":"Filius Flitwick","otherName":"","level":2000,"picture":"filius-flitwick-6980268984228399346.jpg","powers":["Deconstruction","Energy Blasts","Energy Constructs","Fire Control","Force Fields","Heal","Intelligence","Levitation","Light Control","Magic","Master Tactician","Mind Control","Mind Control Resistance","Petrification","Stamina","Telekinesis","Telepathy Resistance","Teleportation","Transmutation","Water Control","Accelerated Healing","Biokinesis","Dark Arts","Dark Magic","Darkforce Manipulation","Element Control","Endurance","Indomitable Will","Longevity","Plant Control","Telepathy"],"origin":"/filius-flitwick/10-13801/","alignment":"Hero"}