{"id":"hal-jordan--7706329339964472958","name":"Green Lantern","otherName":"Hal Jordan","level":411000,"picture":"hal-jordan--7706329339964472958.jpg","powers":["Agility","Animation","Cold Resistance","Durability","Energy Absorption","Energy Armor","Energy Beams","Energy Blasts","Energy Constructs","Energy Manipulation","Energy Resistance","Fire Resistance","Flight","Force Fields","Heat Resistance","Illumination","Indomitable Will","Intelligence","Interstellar Travel","Invulnerability","Lantern Power Ring","Levitation","Marksmanship","Master Tactician","Mind Control Resistance","Peak Human Condition","Portal Creation","Projection","Reflexes","Stamina","Super Speed","Super Strength","Teleportation","Weapon Creation","Weapon Summoning","Weapon-based Powers","Weapons Master","Willpower Manipulation","Ability Shift","Absorption","Accelerated Development","Accelerated Healing","Adaptation","Attack Reflection","Cosmic Awareness","Danger Sense","Dexterity","Dimensional Awareness","Dimensional Travel","Electricity Resistance","Emotional Power Up","Endurance","Enhanced Hearing","Enhanced Memory","Enhanced Senses","Enhanced Sight","Explosion Manipulation","Extrasensory Perception","Hacking","Heat Generation","Illusion Resistance","Information Analysis","Intangibility","Invisibility","Jump","Light Control","Master Martial Artist","Non-Physical Interaction","Omnilingualism","Phasing","Possession Resistance","Power Suit","Preparation","Radar Sense","Radiation Immunity","Reactive Power Level","Resurrection","Self-Sustenance","Spatial Awareness","Statistics Amplification","Stealth","Telepathy Resistance","Vehicular Mastery","Vision - Microscopic","Vision - Night","Vision - Telescopic","Vision - X-Ray","Existence Erasure Resistance","Hypnokinesis","Matter Manipulation","Mind Control","Pocket Dimensions","Psionic Powers","Regeneration","Telepathy","Time Travel"],"origin":"/green-lantern/10-697/","alignment":"Hero"}