{"id":"helios--1874216450974986449","name":"Cyborg Helios","otherName":"Helios","level":388000,"picture":"helios--1874216450974986449.jpg","powers":["Absorption","Accelerated Healing","Agility","Attack Negation","Attack Reflection","Berserk Mode","Bloodlust","Bullet Time","Cyborgization","Damage Boost","Damage Reduction","Damage Transferal","Dexterity","Durability","Electricity Resistance","Emotional Power Up","Endurance","Energy Absorption","Energy Armor","Energy Beams","Energy Blasts","Energy Constructs","Energy Embodiment","Energy Manipulation","Energy Resistance","Fear Manipulation","Fire Control","Fire Resistance","Flight","Heat Generation","Heat Resistance","Insanity","Intelligence","Invulnerability","Jump","Levitation","Light Control","Marksmanship","Master Martial Artist","Master Tactician","Nanotechnology","Power Absorption","Power Nullifier","Radiation Immunity","Rage Power","Regeneration","Stamina","Technopath/Cyberpath","Vision - Infrared","Vision - Microscopic","Vision - Night","Vision - Telescopic","Vision - Thermal","Vision - X-Ray","Adaptation","Air Control","Camouflage","Darkforce Manipulation","Enhanced Hearing","Enhanced Memory","Enhanced Senses","Enhanced Sight","Enhanced Smell","Hellfire Resistance","Immortality","Projection","Reflexes","Self-Sustenance","Shapeshifting","Spaceflight","Technological Possession","Teleportation","Underwater breathing"],"origin":"/cyborg-helios/10-24448/","alignment":"Hero"}