{"id":"ho-oh-6577925738918989519","name":"Ho-Oh","otherName":"","level":3000,"picture":"ho-oh-6577925738918989519.jpg","powers":["Blessed","Damage Reduction","Divine Powers","Flight","Heal","Immortality","Life Manipulation","Purification","Zenith","Agility","Animal Attributes","Curse Manipulation","Illumination","Light Control","Power Augmentation","Power Bestowal","Power Modification","Rainbow Energy","Sealing","Wing Manifestation","Organic Manipulation","Plot Manipulation"],"origin":"/ho-oh/10-13581/","alignment":"Hero"}