{"id":"hotaru-tomoe--286816582848658726","name":"Sailor Saturn","otherName":"Hotaru Tomoe","level":182000,"picture":"hotaru-tomoe--286816582848658726.jpg","powers":["Element Control","Flight","Force Fields","Magic","Astral Projection","Cyborgization","Death Manipulation","Dimensional Travel","Durability Negation","Enhanced Senses","Existence Erasure Resistance","Heal","Illusions","Immortality","Matter Manipulation","Mind Control Resistance","Non-Corporeal","Non-Physical Interaction","Postcognition","Power Nullifier","Precognition","Radiation Immunity","Reality Warping","Reality Warping Resistance","Soul Manipulation","Soul Resistance","Telepathy","Teleportation"],"origin":"/sailor-saturn/10-21843/","alignment":"Hero"}