{"id":"kim-possible--6946741774550939601","name":"Kim Possible","otherName":"","level":71,"picture":"kim-possible--6946741774550939601.jpg","powers":["Acrobatics","Agility","Dexterity","Durability","Intelligence","Marksmanship","Master Martial Artist","Peak Human Condition","Reflexes","Stamina","Stealth","Super Speed","Super Strength","Weapon-based Powers","Weapons Master","Endurance","Enhanced Senses","Indomitable Will","Jump","Luck","Master Tactician","Preparation","Flight","Power Suit","The Fourth Wall"],"origin":"/kim-possible/10-10900/","alignment":"Hero"}