{"id":"kirei-kotomine--651790563622042647","name":"Kirei Kotomine (Fate/Zero)","otherName":"Kirei Kotomine","level":135,"picture":"kirei-kotomine--651790563622042647.jpg","powers":["Accelerated Healing","Acrobatics","Agility","Apathy","Durability","Endurance","Marksmanship","Master Martial Artist","Master Tactician","Peak Human Condition","Reflexes","Stamina","Super Strength","Swordsmanship","Weapon-based Powers","Weapons Master","Creation","Damage Boost","Dexterity","Information Analysis","Instinctive Reaction","Jump","Stealth","Weapon Creation","Pain Suppression","Perfect Recollection","Photographic Reflexes","Pressure Points","Regeneration","Sealing"],"origin":"/kirei-kotomine-fatezero/10-27269/","alignment":"Hero"}