{"id":"levi-ackerman--1030452808308602971","name":"Levi Ackerman","otherName":"","level":109,"picture":"levi-ackerman--1030452808308602971.jpg","powers":["Acrobatics","Agility","Dexterity","Endurance","Intelligence","Marksmanship","Master Martial Artist","Master Tactician","Reflexes","Stamina","Stealth","Swordsmanship","Weapons Master","Awakened Power","Berserk Mode","Bloodlust","Disguise Mastery","Enhanced Hearing","Enhanced Memory","Enhanced Senses","Enhanced Sight","Explosion Manipulation","Jump","Pain Suppression","Weapon-based Powers"],"origin":"/levi-ackerman/10-19530/","alignment":"Hero"}