{"id":"magolor--5550344349632150461","name":"Magolor","otherName":"","level":84000,"picture":"magolor--5550344349632150461.jpg","powers":["Antimatter Manipulation","Arcane Magic","Arcane Magic","Astral Projection","Astral Travel","Reality Warping","Causality Manipulation","Chaos Magic","Dark Arts","Dark Magic","Energy Beams","Energy Blasts","Godly Physiology","Homing Attack","Magic","Portal Creation","Rainbow Energy","Self-Sustenance","Spatial Communication","Curse Manipulation","Power Modification"],"origin":"/magolor/10-31367/","alignment":"Hero"}