{"id":"moro--3469189000684550900","name":"Planet-Eater Moro","otherName":"Moro","level":50000,"picture":"moro--3469189000684550900.jpg","powers":["Durability","Endurance","Intelligence","Jump","Master Martial Artist","Stamina","Super Speed","Super Strength","Acrobatics","Agility","Cold Resistance","Energy Absorption","Energy Blasts","Enhanced Senses","Flight","Heat Generation","Heat Resistance","Illusions","Invulnerability","Master Tactician","Power Mimicry","Reflexes","Stealth","Telekinesis","Telepathy","Accelerated Healing","Energy Manipulation","Immortality","Interstellar Travel"],"origin":"/planet-eater-moro/10-16546/","alignment":"Villain"}