{"id":"orthopterran-4761384269387745045","name":"Crashhopper","otherName":"Orthopterran","level":288,"picture":"orthopterran-4761384269387745045.jpg","powers":["Acrobatics","Agility","Animal Attributes","Animal Oriented Powers","Durability","Intelligence","Jump","Peak Human Condition","Stamina","Super Speed","Super Strength","Accelerated Healing","Adaptation","Danger Sense","Dexterity","Endurance","Enhanced Condition","Enhanced Senses","Enhanced Sight","Heat Resistance","Longevity","Master Martial Artist","Natural Armor","Natural Weapons","Pressure Points","Radiation Immunity","Reflexes","Stealth","Vision - Night","Wallcrawling","Seismic Power","Shockwaves Generation"],"origin":"/crashhopper/10-22155/","alignment":"Hero"}