{"id":"ragnarok--9184870727141276128","name":"Ragnarok","otherName":"","level":1000,"picture":"ragnarok--9184870727141276128.jpg","powers":["Accelerated Development","Acrobatics","Agility","Durability","Endurance","Energy Beams","Energy Blasts","Enhanced Condition","Heal","Intelligence","Jump","Marksmanship","Master Martial Artist","Master Tactician","Peak Human Condition","Stamina","Stealth","Super Speed","Super Strength","Accelerated Healing","Cold Resistance","Dexterity","Electricity Resistance","Enhanced Senses","Fire Resistance","Flight","Heat Resistance","Invulnerability","Longevity","Radiation Immunity","Teleportation","Vaporising Beams","Vehicular Mastery"],"origin":"/ragnarok/10-28189/","alignment":"Villain"}