{"id":"remus-lupin-5722127195619609684","name":"Remus Lupin","otherName":"","level":1000,"picture":"remus-lupin-5722127195619609684.jpg","powers":["Accelerated Healing","Animal Attributes","Biokinesis","Deconstruction","Energy Blasts","Energy Constructs","Fire Control","Force Fields","Heal","Indomitable Will","Intelligence","Levitation","Light Control","Magic","Petrification","Shapeshifting","Telekinesis","Telepathy","Teleportation","Transmutation","Animal Oriented Powers","Dark Arts","Dark Magic","Mind Control","Mind Control Resistance","Plant Control","Telepathy Resistance","Water Control"],"origin":"/remus-lupin/10-13800/","alignment":"Hero"}