{"id":"selina-kyle-4675225231329478700","name":"Catwoman","otherName":"Selina Kyle","level":98,"picture":"selina-kyle-4675225231329478700.jpg","powers":["Acrobatics","Agility","Animal Attributes","Dexterity","Durability","Endurance","Enhanced Thievery","Hacking","Intelligence","Marksmanship","Master Martial Artist","Natural Weapons","Peak Human Condition","Reflexes","Stamina","Stealth","Wallcrawling","Weapons Master","Element Control","Instinctive Reaction","Light Control","Master Tactician","Surface Scaling","Vision - X-Ray","Weapon-based Powers"],"origin":"/catwoman/10-16516/","alignment":"Hero"}