{"id":"speed-o'-sound-sonic--3423508504574997468","name":"Speed-o'-Sound Sonic","otherName":"","level":440,"picture":"speed-o'-sound-sonic--3423508504574997468.jpg","powers":["Acrobatics","Afterimage Creation","Dexterity","Endurance","Enhanced Hearing","Enhanced Senses","Enhanced Sight","Enhanced Smell","Enhanced Touch","Ninjutsu","Reflexes","Smoke Manipulation","Stamina","Swordsmanship","Weapons Master","Agility","Bloodlust","Cold Resistance","Explosion Manipulation","Heat Resistance","Homing Attack","Jump","Master Martial Artist","Master Tactician","Wind Control","Electrokinesis","Invisibility"],"origin":"/speed-o-sound-sonic/10-21918/","alignment":"Villain"}