{"id":"titanus-camazotz-7522512672871301256","name":"Camazotz","otherName":"Titanus Camazotz","level":1000,"picture":"titanus-camazotz-7522512672871301256.jpg","powers":["Animal Attributes","Animal Oriented Powers","Echolocation","Enhanced Hearing","Flight","Large Size","Natural Armor","Natural Weapons","Radiation Immunity","Sonic Scream","Cold Resistance","Dig","Electricity Resistance","Energy Resistance","Enhanced Senses","Enhanced Smell","Fire Resistance","Heat Resistance","Jaw Strength","Subterranean","Summoning","Animal Control","Grappling/Climbing","Multiple Limbs","Radar Sense","Radiation Absorption","Self-Sustenance","Weather Control"],"origin":"/camazotz/10-30165/","alignment":"Villain"}