{"id":"victor-stone--7126270703681255693","name":"Black Lantern","otherName":"Victor Stone","level":60000,"picture":"victor-stone--7126270703681255693.jpg","powers":["Awakened Power","Berserk Mode","Bloodlust","Corruption","Death Touch","Durability","Electrokinesis","Energy Beams","Enhanced Memory","Flight","Hacking","Illusion Resistance","Intelligence","Interstellar Travel","Power Suit","Reflexes","Stamina","Super Speed","Super Strength","Technopath/Cyberpath","Weapon-based Powers","Zombie Physiology","Ability Shift","Absorption","Accelerated Development","Accelerated Healing","Adaptation","Agility","Audio Control","Cold Resistance","Damage Boost","Danger Sense","Death Manipulation","Dexterity","Elasticity","Electrical Transport","Endurance","Energy Armor","Energy Blasts","Energy Manipulation","Enhanced Hearing","Enhanced Senses","Enhanced Sight","Fire Resistance","Force Fields","Heat Generation","Heat Resistance","Information Analysis","Intuitive aptitude","Invulnerability","Jump","Lantern Power Ring","Magnetism","Marksmanship","Mechanical Aptitude","Photographic Reflexes","Power Absorption","Radar Sense","Regeneration","Stealth","Teleportation","Transformation","Vibration Manipulation","Vision - Heat","Vision - Microscopic","Vision - Telescopic","Vision - X-Ray","Weapon Summoning","Weapons Master","Clairvoyance Resistance","Energy Resistance"],"origin":"/black-lantern/10-40179/","alignment":"Villain"}